Tams/__init__.py
Tams/matematika.py
Tams-1.0.0.dist-info/LICENSE
Tams-1.0.0.dist-info/METADATA
Tams-1.0.0.dist-info/WHEEL
Tams-1.0.0.dist-info/top_level.txt
Tams-1.0.0.dist-info/RECORD
