Metadata-Version: 2.1
Name: Tams
Version: 1.0.0
Summary: Package matematika sederhana
Home-page: UNKNOWN
Author: Arya Wiratama
Author-email: aryawiratama2401@gmail.com
License: UNKNOWN
Platform: UNKNOWN
Requires-Python: >=3.10
License-File: LICENSE
